deeplite_torch_zoo/__init__.py
deeplite_torch_zoo/postinstall.py
deeplite_torch_zoo/trainer.py
deeplite_torch_zoo/api/__init__.py
deeplite_torch_zoo/api/api.py
deeplite_torch_zoo/api/registries.py
deeplite_torch_zoo/api/datasets/__init__.py
deeplite_torch_zoo/api/datasets/utils.py
deeplite_torch_zoo/api/datasets/classification/__init__.py
deeplite_torch_zoo/api/datasets/classification/cifar.py
deeplite_torch_zoo/api/datasets/classification/flowers102.py
deeplite_torch_zoo/api/datasets/classification/food101.py
deeplite_torch_zoo/api/datasets/classification/imagenet.py
deeplite_torch_zoo/api/datasets/classification/imagenette.py
deeplite_torch_zoo/api/datasets/classification/imagewoof.py
deeplite_torch_zoo/api/datasets/classification/mnist.py
deeplite_torch_zoo/api/datasets/classification/tiny_imagenet.py
deeplite_torch_zoo/api/datasets/classification/vww.py
deeplite_torch_zoo/api/datasets/object_detection/__init__.py
deeplite_torch_zoo/api/datasets/object_detection/utils.py
deeplite_torch_zoo/api/datasets/object_detection/yolo.py
deeplite_torch_zoo/api/datasets/object_detection/configs/SKU-110K.yaml
deeplite_torch_zoo/api/datasets/object_detection/configs/VOC.yaml
deeplite_torch_zoo/api/datasets/object_detection/configs/coco.yaml
deeplite_torch_zoo/api/datasets/object_detection/configs/coco128.yaml
deeplite_torch_zoo/api/datasets/object_detection/configs/coco8.yaml
deeplite_torch_zoo/api/eval/__init__.py
deeplite_torch_zoo/api/eval/classification.py
deeplite_torch_zoo/api/eval/yolo.py
deeplite_torch_zoo/api/eval/zero_cost.py
deeplite_torch_zoo/api/models/__init__.py
deeplite_torch_zoo/api/models/classification/__init__.py
deeplite_torch_zoo/api/models/classification/model_implementation_dict.py
deeplite_torch_zoo/api/models/classification/cifar100/__init__.py
deeplite_torch_zoo/api/models/classification/cifar100/densenet.py
deeplite_torch_zoo/api/models/classification/cifar100/googlenet.py
deeplite_torch_zoo/api/models/classification/cifar100/mobilenetv1.py
deeplite_torch_zoo-2.0.5.dist-info/LICENSE.md
deeplite_torch_zoo-2.0.5.dist-info/METADATA
deeplite_torch_zoo-2.0.5.dist-info/NOTICE.txt
deeplite_torch_zoo-2.0.5.dist-info/WHEEL
deeplite_torch_zoo-2.0.5.dist-info/top_level.txt
deeplite_torch_zoo-2.0.5.dist-info/RECORD
