Metadata-Version: 2.1
Name: deeplite-torch-zoo
Version: 2.0.5
Summary: The deeplite-torch-zoo package is a collection of popular pretrained deep learning models and their datasets for PyTorch framework.
Home-page: https://github.com/Deeplite/deeplite-torch-zoo
Author: Deeplite
Author-email: support@deeplite.ai
License: Multi-licensing
Keywords: deep_neural_network deep_learning zoo model datasets pytorch deeplite
Classifier: Development Status :: 5 - Production/Stable
Classifier: Intended Audience :: Science/Research
Classifier: Intended Audience :: Developers
Classifier: Programming Language :: Python
Classifier: Programming Language :: Python :: 3.6
Classifier: Programming Language :: Python :: 3.7
Classifier: Programming Language :: Python :: 3.8
Classifier: Topic :: Scientific/Engineering :: Artificial Intelligence
Classifier: Topic :: Software Development :: Libraries :: Python Modules
Classifier: Operating System :: POSIX :: Linux
Classifier: Operating System :: MacOS :: MacOS X
Classifier: Natural Language :: English
Classifier: License :: Other/Proprietary License
Classifier: Environment :: Console
License-File: LICENSE.md
License-File: NOTICE.txt
Requires-Dist: setuptools (<65.6.0)
Requires-Dist: urllib3 (==1.26.6)
Requires-Dist: torch (<=2.0.1,>=1.4)
Requires-Dist: opencv-python (<=4.6.0.66)
Requires-Dist: scipy (>=1.4.1)
Requires-Dist: Cython (==0.29.30)
Requires-Dist: tqdm (>=4.46.0)
Requires-Dist: albumentations (==1.0.3)
Requires-Dist: tensorboardX (==2.4.1)
Requires-Dist: pyvww (==0.1.1)
Requires-Dist: timm (==0.9.2)
Requires-Dist: pytorchcv (==0.0.67)
Requires-Dist: texttable (==1.6.4)
Requires-Dist: torchprofile (==0.0.4)
Requires-Dist: addict (==2.4.0)
Requires-Dist: Wand (==0.6.11)
Requires-Dist: pytz
Requires-Dist: pandas
Requires-Dist: tensorboard (>=2.11.2)
Requires-Dist: openmim (==0.3.7)
Requires-Dist: super-gradients (==3.3.0)
Requires-Dist: numpy (==1.21.6)
Requires-Dist: ultralytics (==8.0.145)
